grist_api/__init__.py
grist_api/grist_api.py
grist_api-0.1.1.dist-info/LICENSE
grist_api-0.1.1.dist-info/METADATA
grist_api-0.1.1.dist-info/WHEEL
grist_api-0.1.1.dist-info/top_level.txt
grist_api-0.1.1.dist-info/RECORD
