Metadata-Version: 2.1
Name: grist-api
Version: 0.1.1
Summary: Python client for interacting with Grist
Home-page: https://github.com/gristlabs/py_grist_api
Author: Dmitry Sagalovskiy, Grist Labs
Author-email: dmitry@getgrist.com
License: Apache 2.0
Keywords: grist api database
Classifier: Development Status :: 3 - Alpha
Classifier: Intended Audience :: Developers
Classifier: Topic :: Software Development :: Libraries :: Python Modules 
Classifier: Environment :: Console
Classifier: Operating System :: OS Independent
Classifier: Programming Language :: Python :: 2
Classifier: Programming Language :: Python :: 2.7
Classifier: Programming Language :: Python :: 3
Classifier: Programming Language :: Python :: 3.5
Classifier: Programming Language :: Python :: 3.6
Classifier: Programming Language :: Python :: 3.7
Classifier: Programming Language :: Python :: Implementation :: CPython
License-File: LICENSE
Requires-Dist: future
Requires-Dist: requests
Provides-Extra: test
Requires-Dist: nose ; extra == 'test'
Requires-Dist: coverage ; extra == 'test'
Requires-Dist: vcrpy ; extra == 'test'
